pcacode/__init__.py
pcacode/data/2020年11月中华人民共和国县以上行政区划代码.xlsx
pcacode/data/56_nations.xlsx
pcacode-1.0.5.dist-info/LICENSE
pcacode-1.0.5.dist-info/METADATA
pcacode-1.0.5.dist-info/WHEEL
pcacode-1.0.5.dist-info/top_level.txt
pcacode-1.0.5.dist-info/RECORD
