Metadata-Version: 2.1
Name: pcacode
Version: 1.0.5
Summary: 这是一个从文本中找地名信息和地区码的库
Home-page: https://gitee.com/YHjohn/pcacode
Author: john
Author-email: john19940404@live.com
License: UNKNOWN
Platform: UNKNOWN
Classifier: Programming Language :: Python :: 3
Classifier: License :: OSI Approved :: MIT License
Classifier: Operating System :: OS Independent
Requires-Dist: openpyxl
